src/mcp_server_vegalite/__init__.py
src/mcp_server_vegalite/server.py
orange_mcp_server_vegalite-0.0.1.dist-info/METADATA
orange_mcp_server_vegalite-0.0.1.dist-info/WHEEL
orange_mcp_server_vegalite-0.0.1.dist-info/entry_points.txt
orange_mcp_server_vegalite-0.0.1.dist-info/RECORD
