Metadata-Version: 2.4
Name: orange-mcp-server-vegalite
Version: 0.0.1
Summary: A simple Data Visualization MCP server using Vega-Lite
Requires-Python: >=3.10
Requires-Dist: mcp>=1.0.0
Requires-Dist: vl-convert-python
